vagrant_metadata/__init__.py
vagrant_metadata/metadata.py
vagrant_metadata/provider.py
vagrant_metadata/utils.py
vagrant_metadata/version_box.py
python_vagrant_metadata-0.0.5.dist-info/LICENSE
python_vagrant_metadata-0.0.5.dist-info/METADATA
python_vagrant_metadata-0.0.5.dist-info/WHEEL
python_vagrant_metadata-0.0.5.dist-info/top_level.txt
python_vagrant_metadata-0.0.5.dist-info/RECORD
