Metadata-Version: 2.1
Name: python-vagrant-metadata
Version: 0.0.5
Summary: Can use and parse metadata information of vagrant box
Home-page: https://github.com/LeConTesteur/python-vagrant-metadata
Author: LeConTesteur
Project-URL: Bug Tracker, https://github.com/LeConTesteur/python-vagrant-metadata/issues
Keywords: vagrant
Classifier: License :: OSI Approved :: GNU General Public License v3 or later (GPLv3+)
Requires-Python: >=3.6
License-File: LICENSE
Requires-Dist: packaging
Requires-Dist: dataclasses-json
Requires-Dist: requests
Provides-Extra: tests
Requires-Dist: requests-mock ; extra == 'tests'
Requires-Dist: flake8 ; extra == 'tests'
Requires-Dist: coverage ; extra == 'tests'
